weasel_pipeline/__init__.py
weasel_pipeline/aio.py
weasel_pipeline/config.py
weasel_pipeline/queue.py
weasel_pipeline-1.1.7.dist-info/WHEEL
weasel_pipeline-1.1.7.dist-info/METADATA
weasel_pipeline-1.1.7.dist-info/RECORD
